UzbekistanWeather/__init__.py
UzbekistanWeather/weather.py
weather/__init__.py
weather/weather.py
UzbekistanWeather-1.0.7.dist-info/METADATA
UzbekistanWeather-1.0.7.dist-info/WHEEL
UzbekistanWeather-1.0.7.dist-info/top_level.txt
UzbekistanWeather-1.0.7.dist-info/RECORD
