Metadata-Version: 2.1
Name: UzbekistanWeather
Version: 1.0.7
Home-page: https://github.com/sinofarmonovzfkrvjl
Author: Sino
Author-email: farmonovsino@gmail.com
Requires-Dist: requests
Requires-Dist: beautifulsoup4
